Kyber/__init__.py
Kyber/main.py
mini_kyber-0.0.7.dist-info/METADATA
mini_kyber-0.0.7.dist-info/WHEEL
mini_kyber-0.0.7.dist-info/top_level.txt
mini_kyber-0.0.7.dist-info/RECORD
